<?xml version="1.0" encoding="utf-8" ?>
<dwsync>
<file name="shCore.css" server="eloquentdesign.us//" local="129225671400000000" remote="129410435400000000" />
<file name="shCoreDefault.css" server="eloquentdesign.us//" local="129225671400000000" remote="129410435400000000" />
<file name="shCoreDjango.css" server="eloquentdesign.us//" local="129225671400000000" remote="129410435400000000" />
<file name="shCoreEclipse.css" server="eloquentdesign.us//" local="129225671400000000" remote="129410435400000000" />
<file name="shCoreEmacs.css" server="eloquentdesign.us//" local="129225671400000000" remote="129410435400000000" />
<file name="shCoreFadeToGrey.css" server="eloquentdesign.us//" local="129225671400000000" remote="129410435400000000" />
<file name="shCoreMDUltra.css" server="eloquentdesign.us//" local="129225671400000000" remote="129410435400000000" />
<file name="shCoreMidnight.css" server="eloquentdesign.us//" local="129225671400000000" remote="129410436000000000" />
<file name="shCoreRDark.css" server="eloquentdesign.us//" local="129225671400000000" remote="129410436000000000" />
<file name="shThemeDefault.css" server="eloquentdesign.us//" local="129225671400000000" remote="129410436000000000" />
<file name="shThemeDjango.css" server="eloquentdesign.us//" local="129225671400000000" remote="129410436000000000" />
<file name="shThemeEclipse.css" server="eloquentdesign.us//" local="129225671400000000" remote="129410436000000000" />
<file name="shThemeEmacs.css" server="eloquentdesign.us//" local="129225671400000000" remote="129410436000000000" />
<file name="shThemeFadeToGrey.css" server="eloquentdesign.us//" local="129225671400000000" remote="129410436000000000" />
<file name="shThemeMDUltra.css" server="eloquentdesign.us//" local="129225671400000000" remote="129410436000000000" />
<file name="shThemeMidnight.css" server="eloquentdesign.us//" local="129225671400000000" remote="129410436000000000" />
<file name="shThemeRDark.css" server="eloquentdesign.us//" local="129225671400000000" remote="129410436000000000" />
</dwsync>